{
  "annotations": {
    "list": [
      {
        "builtIn": 1,
        "datasource": "-- Grafana --",
        "enable": true,
        "hide": true,
        "iconColor": "rgba(0, 211, 255, 1)",
        "name": "Annotations & Alerts",
        "type": "dashboard"
      }
    ]
  },
  "editable": true,
  "gnetId": null,
  "graphTooltip": 0,
  "id": 10,
  "links": [],
  "panels": [
    {
      "datasource": null,
      "fieldConfig": {
        "defaults": {
          "color": {
            "mode": "palette-classic"
          },
          "custom": {
            "axisLabel": "",
            "axisPlacement": "auto",
            "barAlignment": 0,
            "drawStyle": "line",
            "fillOpacity": 0,
            "gradientMode": "none",
            "hideFrom": {
              "legend": false,
              "tooltip": false,
              "viz": false
            },
            "lineInterpolation": "linear",
            "lineWidth": 1,
            "pointSize": 5,
            "scaleDistribution": {
              "type": "linear"
            },
            "showPoints": "auto",
            "spanNulls": false,
            "stacking": {
              "group": "A",
              "mode": "none"
            },
            "thresholdsStyle": {
              "mode": "off"
            }
          },
          "mappings": [],
          "thresholds": {
            "mode": "absolute",
            "steps": [
              {
                "color": "green",
                "value": null
              },
              {
                "color": "red",
                "value": 80
              }
            ]
          }
        },
        "overrides": [
          {
            "matcher": {
              "id": "byName",
              "options": "dockerhub_ratelimit_login{env=\"fedora\", instance=\"fed120:9100\", job=\"node_exporters_https\"}"
            },
            "properties": [
              {
                "id": "color",
                "value": {
                  "fixedColor": "#5794F2",
                  "mode": "fixed"
                }
              }
            ]
          },
          {
            "matcher": {
              "id": "byName",
              "options": "dockerhub_remaining_nologin{env=\"fedora\", instance=\"fed120:9100\", job=\"node_exporters_https\"}"
            },
            "properties": [
              {
                "id": "color",
                "value": {
                  "fixedColor": "super-light-blue",
                  "mode": "fixed"
                }
              }
            ]
          },
          {
            "matcher": {
              "id": "byName",
              "options": "dockerhub_reset_nologin{env=\"fedora\", instance=\"fed120:9100\", job=\"node_exporters_https\"}"
            },
            "properties": [
              {
                "id": "color",
                "value": {
                  "fixedColor": "dark-red",
                  "mode": "fixed"
                }
              }
            ]
          },
          {
            "matcher": {
              "id": "byName",
              "options": "dockerhub_remaining_login{env=\"fedora\", instance=\"fed120:9100\", job=\"node_exporters_https\"}"
            },
            "properties": [
              {
                "id": "color",
                "value": {
                  "fixedColor": "super-light-red",
                  "mode": "fixed"
                }
              }
            ]
          }
        ]
      },
      "gridPos": {
        "h": 22,
        "w": 24,
        "x": 0,
        "y": 0
      },
      "id": 2,
      "options": {
        "legend": {
          "calcs": [],
          "displayMode": "list",
          "placement": "bottom"
        },
        "tooltip": {
          "mode": "single"
        }
      },
      "targets": [
        {
          "exemplar": true,
          "expr": "dockerhub_ratelimit_login",
          "interval": "",
          "legendFormat": "",
          "refId": "A"
        },
        {
          "exemplar": true,
          "expr": "dockerhub_ratelimit_nologin",
          "hide": false,
          "interval": "",
          "legendFormat": "",
          "refId": "B"
        },
        {
          "exemplar": true,
          "expr": "dockerhub_remaining_nologin",
          "hide": false,
          "interval": "",
          "legendFormat": "",
          "refId": "C"
        },
        {
          "exemplar": true,
          "expr": "dockerhub_remaining_login",
          "hide": false,
          "interval": "",
          "legendFormat": "",
          "refId": "D"
        },
        {
          "exemplar": true,
          "expr": "dockerhub_reset_nologin",
          "hide": false,
          "interval": "",
          "legendFormat": "",
          "refId": "E"
        },
        {
          "exemplar": true,
          "expr": "dockerhub_reset_login",
          "hide": false,
          "interval": "",
          "legendFormat": "",
          "refId": "F"
        }
      ],
      "title": "Docker rate limit",
      "type": "timeseries"
    }
  ],
  "refresh": "",
  "schemaVersion": 30,
  "style": "dark",
  "tags": [],
  "templating": {
    "list": []
  },
  "time": {
    "from": "now-30m",
    "to": "now"
  },
  "timepicker": {},
  "timezone": "",
  "title": "Docker rate limit Copy",
  "uid": "hAOVb3k7k",
  "version": 4
}